MANIFEST.in
README.md
setup.cfg
setup.py
bin/reverse_fastas
bin/update_fastas
furious_fastas/__init__.py
furious_fastas/contaminants.py
furious_fastas/download.py
furious_fastas/fasta.py
furious_fastas/fastas.py
furious_fastas/misc.py
furious_fastas/parse_conf_file.py
furious_fastas/test.py
furious_fastas/test2.py
furious_fastas/test3.py
furious_fastas/uniprot.py
furious_fastas.egg-info/PKG-INFO
furious_fastas.egg-info/SOURCES.txt
furious_fastas.egg-info/dependency_links.txt
furious_fastas.egg-info/requires.txt
furious_fastas.egg-info/top_level.txt
furious_fastas/update/__init__.py
furious_fastas/update/peaks.py
furious_fastas/update/plgs.py