Metadata-Version: 1.1
Name: furious-fastas
Version: 0.1.4
Summary: Module to update the fastas.
Home-page: https://bitbucket.org/MatteoLacki/furious_fastas/src/master/
Author: Mateusz Krzysztof Łącki
Author-email: matteo.lacki@gmail.com
License: UNKNOWN
Keywords: Mass Spectrometry,fastareverse fastas
Platform: UNKNOWN
Classifier: Development Status :: 1 - Planning
Classifier: License :: OSI Approved :: BSD License
Classifier: Intended Audience :: Science/Research
Classifier: Topic :: Scientific/Engineering :: Chemistry
Classifier: Programming Language :: Python :: 3.6
